{"contributors": null, "truncated": false, "text": "A monumental valley\n\n#monumentvalley #navajonation #navajo #utah #Landscape #beauty @ Monument\u2026 https://t.co/L2YLHlJ1vr", "is_quote_status": false, "in_reply_to_status_id": null, "id": 699125607729360896, "favorite_count": 0, "rez": "Navajo Nation Reservation", "source": "<a href=\"http://instagram.com\" rel=\"nofollow\">Instagram</a>", "retweeted": false, "coordinates": {"type": "Point", "coordinates": [-110.1, 36.98333333]}, "timestamp_ms": "1455519508665", "entities": {"user_mentions": [], "symbols": [], "hashtags": [{"indices": [21, 36], "text": "monumentvalley"}, {"indices": [37, 50], "text": "navajonation"}, {"indices": [51, 58], "text": "navajo"}, {"indices": [59, 64], "text": "utah"}, {"indices": [65, 75], "text": "Landscape"}, {"indices": [76, 83], "text": "beauty"}], "urls": [{"url": "https://t.co/L2YLHlJ1vr", "indices": [96, 119], "expanded_url": "https://www.instagram.com/p/BBzDYYwt3KQ/", "display_url": "instagram.com/p/BBzDYYwt3KQ/"}]}, "in_reply_to_screen_name": null, "id_str": "699125607729360896", "retweet_count": 0, "in_reply_to_user_id": null, "favorited": false, "user": {"follow_request_sent": null, "profile_use_background_image": true, "default_profile_image": false, "id": 30184802, "verified": false, "profile_image_url_https": "https://pbs.twimg.com/profile_images/537848830859816960/DwADJwLF_normal.jpeg", "profile_sidebar_fill_color": "FFF7CC", "profile_text_color": "0C3E53", "followers_count": 477, "profile_sidebar_border_color": "F2E195", "id_str": "30184802", "profile_background_color": "BADFCD", "listed_count": 56, "profile_background_image_url_https": "https://abs.twimg.com/images/themes/theme12/bg.gif", "utc_offset": -28800, "statuses_count": 20017, "description": "We've got Payet, Dimitri Payet, I just don't think you understand... Lefty Cockney martial arts' instructor in San Francisco. A Hammer \u2692 a Giant and a Warrior.", "friends_count": 331, "location": "iPhone: 51.512900,-0.065332", "profile_link_color": "FF0000", "profile_image_url": "http://pbs.twimg.com/profile_images/537848830859816960/DwADJwLF_normal.jpeg", "following": null, "geo_enabled": true, "profile_banner_url": "https://pbs.twimg.com/profile_banners/30184802/1417068129", "profile_background_image_url": "http://abs.twimg.com/images/themes/theme12/bg.gif", "name": "\u2692 Steve Rapport \u2692", "lang": "en", "profile_background_tile": false, "favourites_count": 54, "screen_name": "NorthBankNorman", "notifications": null, "url": "http://www.hrksf.com", "created_at": "Fri Apr 10 08:13:36 +0000 2009", "contributors_enabled": false, "time_zone": "Pacific Time (US & Canada)", "protected": false, "default_profile": false, "is_translator": false}, "geo": {"type": "Point", "coordinates": [36.98333333, -110.1]}, "in_reply_to_user_id_str": null, "possibly_sensitive": false, "lang": "ro", "created_at": "Mon Feb 15 06:58:28 +0000 2016", "filter_level": "low", "in_reply_to_status_id_str": null, "place": {"full_name": "Arizona, USA", "url": "https://api.twitter.com/1.1/geo/id/a612c69b44b2e5da.json", "country": "United States", "place_type": "admin", "bounding_box": {"type": "Polygon", "coordinates": [[[-114.818269, 31.332246], [-114.818269, 37.004261], [-109.045153, 37.004261], [-109.045153, 31.332246]]]}, "country_code": "US", "attributes": {}, "id": "a612c69b44b2e5da", "name": "Arizona"}}{"contributors": null, "truncated": false, "text": "Can you recommend anyone for this #job? Channel Coordinator - https://t.co/7C8UDDGQqv #Chandler, AZ #Sales #Hiring", "is_quote_status": false, "in_reply_to_status_id": null, "id": 699122516518764544, "favorite_count": 0, "rez": "Gila River Indian Reservation", "source": "<a href=\"http://tweetmyjobs.com\" rel=\"nofollow\">SafeTweet by TweetMyJOBS</a>", "retweeted": false, "coordinates": {"type": "Point", "coordinates": [-111.8412502, 33.3061605]}, "timestamp_ms": "1455518771663", "entities": {"user_mentions": [], "symbols": [], "hashtags": [{"indices": [34, 38], "text": "job"}, {"indices": [86, 95], "text": "Chandler"}, {"indices": [100, 106], "text": "Sales"}, {"indices": [107, 114], "text": "Hiring"}], "urls": [{"url": "https://t.co/7C8UDDGQqv", "indices": [62, 85], "expanded_url": "http://bit.ly/1HRICX7", "display_url": "bit.ly/1HRICX7"}]}, "in_reply_to_screen_name": null, "id_str": "699122516518764544", "retweet_count": 0, "in_reply_to_user_id": null, "favorited": false, "user": {"follow_request_sent": null, "profile_use_background_image": true, "default_profile_image": false, "id": 714404437, "verified": false, "profile_image_url_https": "https://pbs.twimg.com/profile_images/648939468133523456/NyTLprGc_normal.jpg", "profile_sidebar_fill_color": "DDEEF6", "profile_text_color": "333333", "followers_count": 140, "profile_sidebar_border_color": "FFFFFF", "id_str": "714404437", "profile_background_color": "C0DEED", "listed_count": 140, "profile_background_image_url_https": "https://pbs.twimg.com/profile_background_images/691763308/1116d0a3b93e453d440c336446c34e3e.jpeg", "utc_offset": -18000, "statuses_count": 739, "description": "Vantiv is always looking for the best, brightest and most driven individuals to join our team.", "friends_count": 34, "location": "Cincinnati, Ohio", "profile_link_color": "0084B4", "profile_image_url": "http://pbs.twimg.com/profile_images/648939468133523456/NyTLprGc_normal.jpg", "following": null, "geo_enabled": true, "profile_banner_url": "https://pbs.twimg.com/profile_banners/714404437/1443554216", "profile_background_image_url": "http://pbs.twimg.com/profile_background_images/691763308/1116d0a3b93e453d440c336446c34e3e.jpeg", "name": "VantivCareers", "lang": "en", "profile_background_tile": true, "favourites_count": 9, "screen_name": "VantivCareers", "notifications": null, "url": "http://www.vantiv.com/careers", "created_at": "Tue Jul 24 14:47:47 +0000 2012", "contributors_enabled": false, "time_zone": "Eastern Time (US & Canada)", "protected": false, "default_profile": false, "is_translator": false}, "geo": {"type": "Point", "coordinates": [33.3061605, -111.8412502]}, "in_reply_to_user_id_str": null, "possibly_sensitive": false, "lang": "en", "created_at": "Mon Feb 15 06:46:11 +0000 2016", "filter_level": "low", "in_reply_to_status_id_str": null, "place": {"full_name": "Chandler, AZ", "url": "https://api.twitter.com/1.1/geo/id/52445186970bafb3.json", "country": "United States", "place_type": "city", "bounding_box": {"type": "Polygon", "coordinates": [[[-111.972849, 33.203761], [-111.972849, 33.36114], [-111.788898, 33.36114], [-111.788898, 33.203761]]]}, "country_code": "US", "attributes": {}, "id": "52445186970bafb3", "name": "Chandler"}}{"contributors": null, "truncated": false, "text": "mostly cloudy -&gt; partly cloudy\ntemperature down 72\u00b0F -&gt; 66\u00b0F\nhumidity up 20% -&gt; 26%", "is_quote_status": false, "in_reply_to_status_id": null, "id": 699121009576660993, "favorite_count": 0, "rez": "Gila River Indian Reservation", "source": "<a href=\"http://twitter.com/USACities/cities\" rel=\"nofollow\">Cities</a>", "retweeted": false, "coordinates": {"type": "Point", "coordinates": [-111.78976, 33.32904]}, "timestamp_ms": "1455518412380", "entities": {"user_mentions": [], "symbols": [], "hashtags": [], "urls": []}, "in_reply_to_screen_name": null, "id_str": "699121009576660993", "retweet_count": 0, "in_reply_to_user_id": null, "favorited": false, "user": {"follow_request_sent": null, "profile_use_background_image": true, "default_profile_image": false, "id": 151694289, "verified": false, "profile_image_url_https": "https://pbs.twimg.com/profile_images/699120975594414080/ZoegdkKS_normal.jpg", "profile_sidebar_fill_color": "DDEEF6", "profile_text_color": "333333", "followers_count": 128, "profile_sidebar_border_color": "C0DEED", "id_str": "151694289", "profile_background_color": "C0DEED", "listed_count": 5, "profile_background_image_url_https": "https://abs.twimg.com/images/themes/theme1/bg.png", "utc_offset": -28800, "statuses_count": 25207, "description": "Weather updates, forecast, warnings and information for Gilbert, AZ. Sources: Yahoo! Weather, NOAA, USGS.", "friends_count": 1, "location": "Gilbert, AZ", "profile_link_color": "0084B4", "profile_image_url": "http://pbs.twimg.com/profile_images/699120975594414080/ZoegdkKS_normal.jpg", "following": null, "geo_enabled": true, "profile_background_image_url": "http://abs.twimg.com/images/themes/theme1/bg.png", "name": "Gilbert Weather", "lang": "en", "profile_background_tile": false, "favourites_count": 0, "screen_name": "_GilbertAZ", "notifications": null, "url": null, "created_at": "Fri Jun 04 01:16:41 +0000 2010", "contributors_enabled": false, "time_zone": "Pacific Time (US & Canada)", "protected": false, "default_profile": false, "is_translator": false}, "geo": {"type": "Point", "coordinates": [33.32904, -111.78976]}, "in_reply_to_user_id_str": null, "lang": "en", "created_at": "Mon Feb 15 06:40:12 +0000 2016", "filter_level": "low", "in_reply_to_status_id_str": null, "place": {"full_name": "Gilbert, AZ", "url": "https://api.twitter.com/1.1/geo/id/006b48995ede9bcc.json", "country": "United States", "place_type": "city", "bounding_box": {"type": "Polygon", "coordinates": [[[-111.842244, 33.204608], [-111.842244, 33.385822], [-111.634889, 33.385822], [-111.634889, 33.204608]]]}, "country_code": "US", "attributes": {}, "id": "006b48995ede9bcc", "name": "Gilbert"}}{"contributors": null, "truncated": false, "text": "Champs @youngeastmn \ud83c\udfc0\ud83c\udfc0\ud83c\udfc0 @ Grand Coulee Dam,wa https://t.co/bJ4q4I9453", "is_quote_status": false, "in_reply_to_status_id": null, "id": 699115322960437249, "favorite_count": 0, "rez": "Colville Reservation", "source": "<a href=\"http://instagram.com\" rel=\"nofollow\">Instagram</a>", "retweeted": false, "coordinates": {"type": "Point", "coordinates": [-118.97849952, 47.96615574]}, "timestamp_ms": "1455517056585", "entities": {"user_mentions": [{"id": 372535514, "indices": [7, 19], "id_str": "372535514", "screen_name": "youngeastMN", "name": "SotaBoyTell'em\u00a9\u2122"}], "symbols": [], "hashtags": [], "urls": [{"url": "https://t.co/bJ4q4I9453", "indices": [46, 69], "expanded_url": "https://www.instagram.com/p/BBy-tDEE65P/", "display_url": "instagram.com/p/BBy-tDEE65P/"}]}, "in_reply_to_screen_name": null, "id_str": "699115322960437249", "retweet_count": 0, "in_reply_to_user_id": null, "favorited": false, "user": {"follow_request_sent": null, "profile_use_background_image": true, "default_profile_image": false, "id": 310004355, "verified": false, "profile_image_url_https": "https://pbs.twimg.com/profile_images/600493931638366208/h6ZKC8Gg_normal.jpg", "profile_sidebar_fill_color": "DDEEF6", "profile_text_color": "333333", "followers_count": 277, "profile_sidebar_border_color": "C0DEED", "id_str": "310004355", "profile_background_color": "C0DEED", "listed_count": 5, "profile_background_image_url_https": "https://abs.twimg.com/images/themes/theme1/bg.png", "utc_offset": -21600, "statuses_count": 4194, "description": "Nez Perce, HINU, Health Sport and Exercise Science, Environmental Justice, Nimiipuu Health HR Specialist, UofI Research Assistant", "friends_count": 353, "location": "Lapwai,ID/Lawrence,KS", "profile_link_color": "0084B4", "profile_image_url": "http://pbs.twimg.com/profile_images/600493931638366208/h6ZKC8Gg_normal.jpg", "following": null, "geo_enabled": true, "profile_banner_url": "https://pbs.twimg.com/profile_banners/310004355/1421733968", "profile_background_image_url": "http://abs.twimg.com/images/themes/theme1/bg.png", "name": "No-mercy-Nez-percy", "lang": "en", "profile_background_tile": false, "favourites_count": 912, "screen_name": "chantillie_lace", "notifications": null, "url": null, "created_at": "Fri Jun 03 01:33:32 +0000 2011", "contributors_enabled": false, "time_zone": "Central Time (US & Canada)", "protected": false, "default_profile": true, "is_translator": false}, "geo": {"type": "Point", "coordinates": [47.96615574, -118.97849952]}, "in_reply_to_user_id_str": null, "possibly_sensitive": false, "lang": "en", "created_at": "Mon Feb 15 06:17:36 +0000 2016", "filter_level": "low", "in_reply_to_status_id_str": null, "place": {"full_name": "Washington, USA", "url": "https://api.twitter.com/1.1/geo/id/bc3a38d3d5999b4b.json", "country": "United States", "place_type": "admin", "bounding_box": {"type": "Polygon", "coordinates": [[[-124.848975, 45.543542], [-124.848975, 49.002502], [-116.915989, 49.002502], [-116.915989, 45.543542]]]}, "country_code": "US", "attributes": {}, "id": "bc3a38d3d5999b4b", "name": "Washington"}}{"contributors": null, "truncated": false, "text": "Hendrick\u2019s Cocktail Academy: An Interactive Mixology Event. Saturday, 2/13/16 at 5 PM. \nMixing\u2026 https://t.co/5066ATwoSu", "is_quote_status": false, "in_reply_to_status_id": null, "id": 699116697517584384, "favorite_count": 0, "rez": "Agua Caliente Indian Reservation", "source": "<a href=\"http://instagram.com\" rel=\"nofollow\">Instagram</a>", "retweeted": false, "coordinates": {"type": "Point", "coordinates": [-116.54686297, 33.81938226]}, "timestamp_ms": "1455517384305", "entities": {"user_mentions": [], "symbols": [], "hashtags": [], "urls": [{"url": "https://t.co/5066ATwoSu", "indices": [96, 119], "expanded_url": "https://www.instagram.com/p/BBy_UzJIfxn/", "display_url": "instagram.com/p/BBy_UzJIfxn/"}]}, "in_reply_to_screen_name": null, "id_str": "699116697517584384", "retweet_count": 0, "in_reply_to_user_id": null, "favorited": false, "user": {"follow_request_sent": null, "profile_use_background_image": true, "default_profile_image": false, "id": 2751167781, "verified": false, "profile_image_url_https": "https://pbs.twimg.com/profile_images/504011716448256000/YSWEozAR_normal.jpeg", "profile_sidebar_fill_color": "DDEEF6", "profile_text_color": "333333", "followers_count": 39, "profile_sidebar_border_color": "C0DEED", "id_str": "2751167781", "profile_background_color": "C0DEED", "listed_count": 7, "profile_background_image_url_https": "https://abs.twimg.com/images/themes/theme1/bg.png", "utc_offset": null, "statuses_count": 630, "description": null, "friends_count": 27, "location": "Manhattan Beach", "profile_link_color": "0084B4", "profile_image_url": "http://pbs.twimg.com/profile_images/504011716448256000/YSWEozAR_normal.jpeg", "following": null, "geo_enabled": true, "profile_banner_url": "https://pbs.twimg.com/profile_banners/2751167781/1414086116", "profile_background_image_url": "http://abs.twimg.com/images/themes/theme1/bg.png", "name": "Dr. Wickwire", "lang": "en", "profile_background_tile": false, "favourites_count": 0, "screen_name": "BeachdrmDr", "notifications": null, "url": null, "created_at": "Mon Aug 25 21:00:34 +0000 2014", "contributors_enabled": false, "time_zone": null, "protected": false, "default_profile": true, "is_translator": false}, "geo": {"type": "Point", "coordinates": [33.81938226, -116.54686297]}, "in_reply_to_user_id_str": null, "possibly_sensitive": false, "lang": "en", "created_at": "Mon Feb 15 06:23:04 +0000 2016", "filter_level": "low", "in_reply_to_status_id_str": null, "place": {"full_name": "Palm Springs, CA", "url": "https://api.twitter.com/1.1/geo/id/4265ece9285a2872.json", "country": "United States", "place_type": "city", "bounding_box": {"type": "Polygon", "coordinates": [[[-116.567788, 33.779426], [-116.567788, 33.870733], [-116.466791, 33.870733], [-116.466791, 33.779426]]]}, "country_code": "US", "attributes": {}, "id": "4265ece9285a2872", "name": "Palm Springs"}}{"contributors": null, "truncated": false, "text": "Unexpected Road Trip!\ud83d\udc9e\n#crushaz #myvalentine #mylove @ Chandler,\u2026 https://t.co/008a6FucgL", "is_quote_status": false, "in_reply_to_status_id": null, "id": 699113415722143744, "favorite_count": 0, "rez": "Gila River Indian Reservation", "source": "<a href=\"http://instagram.com\" rel=\"nofollow\">Instagram</a>", "retweeted": false, "coordinates": {"type": "Point", "coordinates": [-111.841, 33.3033]}, "timestamp_ms": "1455516601864", "entities": {"user_mentions": [], "symbols": [], "hashtags": [{"indices": [23, 31], "text": "crushaz"}, {"indices": [32, 44], "text": "myvalentine"}, {"indices": [45, 52], "text": "mylove"}], "urls": [{"url": "https://t.co/008a6FucgL", "indices": [66, 89], "expanded_url": "https://www.instagram.com/p/BBy91Rtn6HwDM-3neX7guwcT3prnqB36Fhk-es0/", "display_url": "instagram.com/p/BBy91Rtn6HwD\u2026"}]}, "in_reply_to_screen_name": null, "id_str": "699113415722143744", "retweet_count": 0, "in_reply_to_user_id": null, "favorited": false, "user": {"follow_request_sent": null, "profile_use_background_image": true, "default_profile_image": false, "id": 427180938, "verified": false, "profile_image_url_https": "https://pbs.twimg.com/profile_images/686716987175649280/onZWK0VU_normal.jpg", "profile_sidebar_fill_color": "DDEEF6", "profile_text_color": "333333", "followers_count": 258, "profile_sidebar_border_color": "C0DEED", "id_str": "427180938", "profile_background_color": "C0DEED", "listed_count": 0, "profile_background_image_url_https": "https://abs.twimg.com/images/themes/theme1/bg.png", "utc_offset": null, "statuses_count": 1355, "description": "God gives the toughest battles to his strongest soldiers\u2728", "friends_count": 236, "location": null, "profile_link_color": "0084B4", "profile_image_url": "http://pbs.twimg.com/profile_images/686716987175649280/onZWK0VU_normal.jpg", "following": null, "geo_enabled": true, "profile_banner_url": "https://pbs.twimg.com/profile_banners/427180938/1452560925", "profile_background_image_url": "http://abs.twimg.com/images/themes/theme1/bg.png", "name": "Jazmin Torres", "lang": "en", "profile_background_tile": false, "favourites_count": 394, "screen_name": "jazzyteeee", "notifications": null, "url": null, "created_at": "Sat Dec 03 06:32:24 +0000 2011", "contributors_enabled": false, "time_zone": null, "protected": false, "default_profile": true, "is_translator": false}, "geo": {"type": "Point", "coordinates": [33.3033, -111.841]}, "in_reply_to_user_id_str": null, "possibly_sensitive": false, "lang": "en", "created_at": "Mon Feb 15 06:10:01 +0000 2016", "filter_level": "low", "in_reply_to_status_id_str": null, "place": {"full_name": "Chandler, AZ", "url": "https://api.twitter.com/1.1/geo/id/52445186970bafb3.json", "country": "United States", "place_type": "city", "bounding_box": {"type": "Polygon", "coordinates": [[[-111.972849, 33.203761], [-111.972849, 33.36114], [-111.788898, 33.36114], [-111.788898, 33.203761]]]}, "country_code": "US", "attributes": {}, "id": "52445186970bafb3", "name": "Chandler"}}{"contributors": null, "truncated": false, "text": "World Class   https://t.co/9Sb8KyoBRw", "is_quote_status": false, "in_reply_to_status_id": null, "id": 699118985154002945, "favorite_count": 0, "rez": "Gila River Indian Reservation", "source": "<a href=\"http://www.squarespace.com\" rel=\"nofollow\">Squarespace</a>", "retweeted": false, "coordinates": {"type": "Point", "coordinates": [-111.8210866, 33.2664407]}, "timestamp_ms": "1455517929720", "entities": {"user_mentions": [], "symbols": [], "hashtags": [], "urls": [{"url": "https://t.co/9Sb8KyoBRw", "indices": [14, 37], "expanded_url": "http://www.djrokkwilder.com/blog/2016/2/15/blog-wc", "display_url": "djrokkwilder.com/blog/2016/2/15\u2026"}]}, "in_reply_to_screen_name": null, "id_str": "699118985154002945", "retweet_count": 0, "in_reply_to_user_id": null, "favorited": false, "user": {"follow_request_sent": null, "profile_use_background_image": true, "default_profile_image": false, "id": 308018168, "verified": false, "profile_image_url_https": "https://pbs.twimg.com/profile_images/537734787973120000/hQlSpF9A_normal.jpeg", "profile_sidebar_fill_color": "DDEEF6", "profile_text_color": "333333", "followers_count": 777, "profile_sidebar_border_color": "C0DEED", "id_str": "308018168", "profile_background_color": "000000", "listed_count": 6, "profile_background_image_url_https": "https://pbs.twimg.com/profile_background_images/476201290595196929/JzRDS4q5.jpeg", "utc_offset": -28800, "statuses_count": 764, "description": "Music = Life\nAll I need are my turntables, some vinyl, and drums to keep me sane.", "friends_count": 978, "location": "Chandler, AZ", "profile_link_color": "ABB8C2", "profile_image_url": "http://pbs.twimg.com/profile_images/537734787973120000/hQlSpF9A_normal.jpeg", "following": null, "geo_enabled": true, "profile_banner_url": "https://pbs.twimg.com/profile_banners/308018168/1434583645", "profile_background_image_url": "http://pbs.twimg.com/profile_background_images/476201290595196929/JzRDS4q5.jpeg", "name": "DJ Rokkwilder", "lang": "en", "profile_background_tile": true, "favourites_count": 115, "screen_name": "djrokkwilder", "notifications": null, "url": "http://djrokkwilder.com", "created_at": "Mon May 30 17:56:31 +0000 2011", "contributors_enabled": false, "time_zone": "Pacific Time (US & Canada)", "protected": false, "default_profile": false, "is_translator": false}, "geo": {"type": "Point", "coordinates": [33.2664407, -111.8210866]}, "in_reply_to_user_id_str": null, "possibly_sensitive": false, "lang": "en", "created_at": "Mon Feb 15 06:32:09 +0000 2016", "filter_level": "low", "in_reply_to_status_id_str": null, "place": {"full_name": "Chandler, AZ", "url": "https://api.twitter.com/1.1/geo/id/52445186970bafb3.json", "country": "United States", "place_type": "city", "bounding_box": {"type": "Polygon", "coordinates": [[[-111.972849, 33.203761], [-111.972849, 33.36114], [-111.788898, 33.36114], [-111.788898, 33.203761]]]}, "country_code": "US", "attributes": {}, "id": "52445186970bafb3", "name": "Chandler"}}{"contributors": null, "truncated": false, "text": "My\ud83d\udc99Crush\ud83d\udc8b\ud83d\udc3c #R3alzyou #jauz #crush2016 @ Rawhide Western Town https://t.co/9UJbqhJT4X", "is_quote_status": false, "in_reply_to_status_id": null, "id": 699116042119811072, "favorite_count": 0, "rez": "Gila River Indian Reservation", "source": "<a href=\"http://instagram.com\" rel=\"nofollow\">Instagram</a>", "retweeted": false, "coordinates": {"type": "Point", "coordinates": [-111.98350014, 33.27027355]}, "timestamp_ms": "1455517228046", "entities": {"user_mentions": [], "symbols": [], "hashtags": [{"indices": [11, 20], "text": "R3alzyou"}, {"indices": [21, 26], "text": "jauz"}, {"indices": [27, 37], "text": "crush2016"}], "urls": [{"url": "https://t.co/9UJbqhJT4X", "indices": [61, 84], "expanded_url": "https://www.instagram.com/p/BBy_BsqhQUSBtzEZ736xNuq-M33d19VsACoyQU0/", "display_url": "instagram.com/p/BBy_BsqhQUSB\u2026"}]}, "in_reply_to_screen_name": null, "id_str": "699116042119811072", "retweet_count": 0, "in_reply_to_user_id": null, "favorited": false, "user": {"follow_request_sent": null, "profile_use_background_image": true, "default_profile_image": false, "id": 921297049, "verified": false, "profile_image_url_https": "https://pbs.twimg.com/profile_images/697721629384704000/JlVEIdQP_normal.jpg", "profile_sidebar_fill_color": "DDEEF6", "profile_text_color": "333333", "followers_count": 610, "profile_sidebar_border_color": "C0DEED", "id_str": "921297049", "profile_background_color": "C0DEED", "listed_count": 7, "profile_background_image_url_https": "https://abs.twimg.com/images/themes/theme1/bg.png", "utc_offset": null, "statuses_count": 3426, "description": "Insta: shinelikeasunflower R3ALZ~~~Be the Best Version you can be", "friends_count": 564, "location": null, "profile_link_color": "0084B4", "profile_image_url": "http://pbs.twimg.com/profile_images/697721629384704000/JlVEIdQP_normal.jpg", "following": null, "geo_enabled": true, "profile_banner_url": "https://pbs.twimg.com/profile_banners/921297049/1450412026", "profile_background_image_url": "http://abs.twimg.com/images/themes/theme1/bg.png", "name": "Kaylee Glenn", "lang": "en", "profile_background_tile": false, "favourites_count": 3275, "screen_name": "kglenncoco", "notifications": null, "url": null, "created_at": "Fri Nov 02 15:59:18 +0000 2012", "contributors_enabled": false, "time_zone": null, "protected": false, "default_profile": true, "is_translator": false}, "geo": {"type": "Point", "coordinates": [33.27027355, -111.98350014]}, "in_reply_to_user_id_str": null, "possibly_sensitive": false, "lang": "en", "created_at": "Mon Feb 15 06:20:28 +0000 2016", "filter_level": "low", "in_reply_to_status_id_str": null, "place": {"full_name": "Arizona, USA", "url": "https://api.twitter.com/1.1/geo/id/a612c69b44b2e5da.json", "country": "United States", "place_type": "admin", "bounding_box": {"type": "Polygon", "coordinates": [[[-114.818269, 31.332246], [-114.818269, 37.004261], [-109.045153, 37.004261], [-109.045153, 31.332246]]]}, "country_code": "US", "attributes": {}, "id": "a612c69b44b2e5da", "name": "Arizona"}}{"contributors": null, "truncated": false, "text": "\u2764\ufe0f @ Crush Az https://t.co/yQiETcJp5f", "is_quote_status": false, "in_reply_to_status_id": null, "id": 699111438527422464, "favorite_count": 0, "rez": "Gila River Indian Reservation", "source": "<a href=\"http://instagram.com\" rel=\"nofollow\">Instagram</a>", "retweeted": false, "coordinates": {"type": "Point", "coordinates": [-111.98274733, 33.27003337]}, "timestamp_ms": "1455516130464", "entities": {"user_mentions": [], "symbols": [], "hashtags": [], "urls": [{"url": "https://t.co/yQiETcJp5f", "indices": [14, 37], "expanded_url": "https://www.instagram.com/p/BBy88CIBFn_AbfgbNJBO_8_3Z4I3Aif9HOEIr40/", "display_url": "instagram.com/p/BBy88CIBFn_A\u2026"}]}, "in_reply_to_screen_name": null, "id_str": "699111438527422464", "retweet_count": 0, "in_reply_to_user_id": null, "favorited": false, "user": {"follow_request_sent": null, "profile_use_background_image": true, "default_profile_image": false, "id": 525874219, "verified": false, "profile_image_url_https": "https://pbs.twimg.com/profile_images/694793347559391232/LC_zwCvs_normal.jpg", "profile_sidebar_fill_color": "E5507E", "profile_text_color": "362720", "followers_count": 565, "profile_sidebar_border_color": "000000", "id_str": "525874219", "profile_background_color": "040ED1", "listed_count": 3, "profile_background_image_url_https": "https://pbs.twimg.com/profile_background_images/676887106/be878852ea16e1bfb3864ee0c1208927.jpeg", "utc_offset": -14400, "statuses_count": 6582, "description": "sing it again rookie biotch", "friends_count": 449, "location": "Santa Clarita, CA", "profile_link_color": "3B94D9", "profile_image_url": "http://pbs.twimg.com/profile_images/694793347559391232/LC_zwCvs_normal.jpg", "following": null, "geo_enabled": true, "profile_banner_url": "https://pbs.twimg.com/profile_banners/525874219/1434816312", "profile_background_image_url": "http://pbs.twimg.com/profile_background_images/676887106/be878852ea16e1bfb3864ee0c1208927.jpeg", "name": "Luke Nilan", "lang": "en", "profile_background_tile": true, "favourites_count": 7279, "screen_name": "luke_nilan", "notifications": null, "url": null, "created_at": "Fri Mar 16 00:12:37 +0000 2012", "contributors_enabled": false, "time_zone": "Atlantic Time (Canada)", "protected": false, "default_profile": false, "is_translator": false}, "geo": {"type": "Point", "coordinates": [33.27003337, -111.98274733]}, "in_reply_to_user_id_str": null, "possibly_sensitive": false, "lang": "tl", "created_at": "Mon Feb 15 06:02:10 +0000 2016", "filter_level": "low", "in_reply_to_status_id_str": null, "place": {"full_name": "Arizona, USA", "url": "https://api.twitter.com/1.1/geo/id/a612c69b44b2e5da.json", "country": "United States", "place_type": "admin", "bounding_box": {"type": "Polygon", "coordinates": [[[-114.818269, 31.332246], [-114.818269, 37.004261], [-109.045153, 37.004261], [-109.045153, 31.332246]]]}, "country_code": "US", "attributes": {}, "id": "a612c69b44b2e5da", "name": "Arizona"}}{"contributors": null, "truncated": false, "text": "\ud83d\udc9e\ud83c\udfc0 @ Grand Coulee Dam,wa https://t.co/BY99v2I3qe", "is_quote_status": false, "in_reply_to_status_id": null, "id": 699117610881937408, "favorite_count": 0, "rez": "Colville Reservation", "source": "<a href=\"http://instagram.com\" rel=\"nofollow\">Instagram</a>", "retweeted": false, "coordinates": {"type": "Point", "coordinates": [-118.97849952, 47.96615574]}, "timestamp_ms": "1455517602068", "entities": {"user_mentions": [], "symbols": [], "hashtags": [], "urls": [{"url": "https://t.co/BY99v2I3qe", "indices": [25, 48], "expanded_url": "https://www.instagram.com/p/BBy_vpfE66s/", "display_url": "instagram.com/p/BBy_vpfE66s/"}]}, "in_reply_to_screen_name": null, "id_str": "699117610881937408", "retweet_count": 0, "in_reply_to_user_id": null, "favorited": false, "user": {"follow_request_sent": null, "profile_use_background_image": true, "default_profile_image": false, "id": 310004355, "verified": false, "profile_image_url_https": "https://pbs.twimg.com/profile_images/600493931638366208/h6ZKC8Gg_normal.jpg", "profile_sidebar_fill_color": "DDEEF6", "profile_text_color": "333333", "followers_count": 277, "profile_sidebar_border_color": "C0DEED", "id_str": "310004355", "profile_background_color": "C0DEED", "listed_count": 5, "profile_background_image_url_https": "https://abs.twimg.com/images/themes/theme1/bg.png", "utc_offset": -21600, "statuses_count": 4196, "description": "Nez Perce, HINU, Health Sport and Exercise Science, Environmental Justice, Nimiipuu Health HR Specialist, UofI Research Assistant", "friends_count": 353, "location": "Lapwai,ID/Lawrence,KS", "profile_link_color": "0084B4", "profile_image_url": "http://pbs.twimg.com/profile_images/600493931638366208/h6ZKC8Gg_normal.jpg", "following": null, "geo_enabled": true, "profile_banner_url": "https://pbs.twimg.com/profile_banners/310004355/1421733968", "profile_background_image_url": "http://abs.twimg.com/images/themes/theme1/bg.png", "name": "No-mercy-Nez-percy", "lang": "en", "profile_background_tile": false, "favourites_count": 912, "screen_name": "chantillie_lace", "notifications": null, "url": null, "created_at": "Fri Jun 03 01:33:32 +0000 2011", "contributors_enabled": false, "time_zone": "Central Time (US & Canada)", "protected": false, "default_profile": true, "is_translator": false}, "geo": {"type": "Point", "coordinates": [47.96615574, -118.97849952]}, "in_reply_to_user_id_str": null, "possibly_sensitive": false, "lang": "en", "created_at": "Mon Feb 15 06:26:42 +0000 2016", "filter_level": "low", "in_reply_to_status_id_str": null, "place": {"full_name": "Washington, USA", "url": "https://api.twitter.com/1.1/geo/id/bc3a38d3d5999b4b.json", "country": "United States", "place_type": "admin", "bounding_box": {"type": "Polygon", "coordinates": [[[-124.848975, 45.543542], [-124.848975, 49.002502], [-116.915989, 49.002502], [-116.915989, 45.543542]]]}, "country_code": "US", "attributes": {}, "id": "bc3a38d3d5999b4b", "name": "Washington"}}{"contributors": null, "truncated": false, "text": "Had an Awesum time Ballin this weekend\ud83c\udfc0\ud83c\udfc0\ud83c\udfc0 #lapwai @ Grand Coulee, Washington https://t.co/49pINzeGhV", "is_quote_status": false, "in_reply_to_status_id": null, "id": 699116050714071040, "favorite_count": 0, "rez": "Colville Reservation", "source": "<a href=\"http://instagram.com\" rel=\"nofollow\">Instagram</a>", "retweeted": false, "coordinates": {"type": "Point", "coordinates": [-119.00166667, 47.93972222]}, "timestamp_ms": "1455517230095", "entities": {"user_mentions": [], "symbols": [], "hashtags": [{"indices": [42, 49], "text": "lapwai"}], "urls": [{"url": "https://t.co/49pINzeGhV", "indices": [77, 100], "expanded_url": "https://www.instagram.com/p/BBy_CPbk65m/", "display_url": "instagram.com/p/BBy_CPbk65m/"}]}, "in_reply_to_screen_name": null, "id_str": "699116050714071040", "retweet_count": 0, "in_reply_to_user_id": null, "favorited": false, "user": {"follow_request_sent": null, "profile_use_background_image": true, "default_profile_image": false, "id": 310004355, "verified": false, "profile_image_url_https": "https://pbs.twimg.com/profile_images/600493931638366208/h6ZKC8Gg_normal.jpg", "profile_sidebar_fill_color": "DDEEF6", "profile_text_color": "333333", "followers_count": 277, "profile_sidebar_border_color": "C0DEED", "id_str": "310004355", "profile_background_color": "C0DEED", "listed_count": 5, "profile_background_image_url_https": "https://abs.twimg.com/images/themes/theme1/bg.png", "utc_offset": -21600, "statuses_count": 4195, "description": "Nez Perce, HINU, Health Sport and Exercise Science, Environmental Justice, Nimiipuu Health HR Specialist, UofI Research Assistant", "friends_count": 353, "location": "Lapwai,ID/Lawrence,KS", "profile_link_color": "0084B4", "profile_image_url": "http://pbs.twimg.com/profile_images/600493931638366208/h6ZKC8Gg_normal.jpg", "following": null, "geo_enabled": true, "profile_banner_url": "https://pbs.twimg.com/profile_banners/310004355/1421733968", "profile_background_image_url": "http://abs.twimg.com/images/themes/theme1/bg.png", "name": "No-mercy-Nez-percy", "lang": "en", "profile_background_tile": false, "favourites_count": 912, "screen_name": "chantillie_lace", "notifications": null, "url": null, "created_at": "Fri Jun 03 01:33:32 +0000 2011", "contributors_enabled": false, "time_zone": "Central Time (US & Canada)", "protected": false, "default_profile": true, "is_translator": false}, "geo": {"type": "Point", "coordinates": [47.93972222, -119.00166667]}, "in_reply_to_user_id_str": null, "possibly_sensitive": false, "lang": "en", "created_at": "Mon Feb 15 06:20:30 +0000 2016", "filter_level": "low", "in_reply_to_status_id_str": null, "place": {"full_name": "Washington, USA", "url": "https://api.twitter.com/1.1/geo/id/bc3a38d3d5999b4b.json", "country": "United States", "place_type": "admin", "bounding_box": {"type": "Polygon", "coordinates": [[[-124.848975, 45.543542], [-124.848975, 49.002502], [-116.915989, 49.002502], [-116.915989, 45.543542]]]}, "country_code": "US", "attributes": {}, "id": "bc3a38d3d5999b4b", "name": "Washington"}}{"contributors": null, "truncated": false, "text": "special delivery, for me?! thank you baby \ud83d\ude3b\ud83d\udc95\ud83e\udd84 happy Valentine's Day\u2026 https://t.co/ETTvXFKPaZ", "is_quote_status": false, "in_reply_to_status_id": null, "id": 699113295119151104, "favorite_count": 0, "rez": "Agua Caliente Indian Reservation", "source": "<a href=\"http://instagram.com\" rel=\"nofollow\">Instagram</a>", "retweeted": false, "coordinates": {"type": "Point", "coordinates": [-116.5483627, 33.8178215]}, "timestamp_ms": "1455516573110", "entities": {"user_mentions": [], "symbols": [], "hashtags": [], "urls": [{"url": "https://t.co/ETTvXFKPaZ", "indices": [69, 92], "expanded_url": "https://www.instagram.com/p/BBy9x23kyEAQ27ukwD2Qtigp055wfAfJJK5XjI0/", "display_url": "instagram.com/p/BBy9x23kyEAQ\u2026"}]}, "in_reply_to_screen_name": null, "id_str": "699113295119151104", "retweet_count": 0, "in_reply_to_user_id": null, "favorited": false, "user": {"follow_request_sent": null, "profile_use_background_image": true, "default_profile_image": false, "id": 2614219982, "verified": false, "profile_image_url_https": "https://pbs.twimg.com/profile_images/684194743236997125/J3ZlYIQI_normal.jpg", "profile_sidebar_fill_color": "DDEEF6", "profile_text_color": "333333", "followers_count": 169, "profile_sidebar_border_color": "C0DEED", "id_str": "2614219982", "profile_background_color": "C0DEED", "listed_count": 0, "profile_background_image_url_https": "https://abs.twimg.com/images/themes/theme1/bg.png", "utc_offset": null, "statuses_count": 2347, "description": "come along with me where the butterflies are bees.", "friends_count": 156, "location": "4:20|11:11", "profile_link_color": "0084B4", "profile_image_url": "http://pbs.twimg.com/profile_images/684194743236997125/J3ZlYIQI_normal.jpg", "following": null, "geo_enabled": true, "profile_banner_url": "https://pbs.twimg.com/profile_banners/2614219982/1454652280", "profile_background_image_url": "http://abs.twimg.com/images/themes/theme1/bg.png", "name": "stina", "lang": "en", "profile_background_tile": false, "favourites_count": 1979, "screen_name": "stinameow", "notifications": null, "url": null, "created_at": "Wed Jul 09 21:07:37 +0000 2014", "contributors_enabled": false, "time_zone": null, "protected": false, "default_profile": true, "is_translator": false}, "geo": {"type": "Point", "coordinates": [33.8178215, -116.5483627]}, "in_reply_to_user_id_str": null, "possibly_sensitive": false, "lang": "en", "created_at": "Mon Feb 15 06:09:33 +0000 2016", "filter_level": "low", "in_reply_to_status_id_str": null, "place": {"full_name": "Palm Springs, CA", "url": "https://api.twitter.com/1.1/geo/id/4265ece9285a2872.json", "country": "United States", "place_type": "city", "bounding_box": {"type": "Polygon", "coordinates": [[[-116.567788, 33.779426], [-116.567788, 33.870733], [-116.466791, 33.870733], [-116.466791, 33.779426]]]}, "country_code": "US", "attributes": {}, "id": "4265ece9285a2872", "name": "Palm Springs"}}{"contributors": null, "truncated": false, "text": "We took a romantic night walk. And came across Palm Springs Art\u2026 https://t.co/6wVYu37iY5", "is_quote_status": false, "in_reply_to_status_id": null, "id": 699125553278877698, "favorite_count": 0, "rez": "Agua Caliente Indian Reservation", "source": "<a href=\"http://instagram.com\" rel=\"nofollow\">Instagram</a>", "retweeted": false, "coordinates": {"type": "Point", "coordinates": [-116.5501709, 33.8244781]}, "timestamp_ms": "1455519495683", "entities": {"user_mentions": [], "symbols": [], "hashtags": [], "urls": [{"url": "https://t.co/6wVYu37iY5", "indices": [65, 88], "expanded_url": "https://www.instagram.com/p/BBzDWzvD74xVxgpl-WmU3ILhkOgpZFjtoib8zs0/", "display_url": "instagram.com/p/BBzDWzvD74xV\u2026"}]}, "in_reply_to_screen_name": null, "id_str": "699125553278877698", "retweet_count": 0, "in_reply_to_user_id": null, "favorited": false, "user": {"follow_request_sent": null, "profile_use_background_image": true, "default_profile_image": false, "id": 920346476, "verified": false, "profile_image_url_https": "https://pbs.twimg.com/profile_images/459485623795986432/6Hg4HcPu_normal.jpeg", "profile_sidebar_fill_color": "DDEEF6", "profile_text_color": "333333", "followers_count": 16, "profile_sidebar_border_color": "C0DEED", "id_str": "920346476", "profile_background_color": "C0DEED", "listed_count": 0, "profile_background_image_url_https": "https://abs.twimg.com/images/themes/theme1/bg.png", "utc_offset": null, "statuses_count": 1408, "description": null, "friends_count": 71, "location": null, "profile_link_color": "800909", "profile_image_url": "http://pbs.twimg.com/profile_images/459485623795986432/6Hg4HcPu_normal.jpeg", "following": null, "geo_enabled": true, "profile_banner_url": "https://pbs.twimg.com/profile_banners/920346476/1398385873", "profile_background_image_url": "http://abs.twimg.com/images/themes/theme1/bg.png", "name": "cassandralopez", "lang": "en", "profile_background_tile": false, "favourites_count": 53, "screen_name": "casandralopez68", "notifications": null, "url": null, "created_at": "Fri Nov 02 04:12:23 +0000 2012", "contributors_enabled": false, "time_zone": null, "protected": false, "default_profile": false, "is_translator": false}, "geo": {"type": "Point", "coordinates": [33.8244781, -116.5501709]}, "in_reply_to_user_id_str": null, "possibly_sensitive": false, "lang": "en", "created_at": "Mon Feb 15 06:58:15 +0000 2016", "filter_level": "low", "in_reply_to_status_id_str": null, "place": {"full_name": "Palm Springs, CA", "url": "https://api.twitter.com/1.1/geo/id/4265ece9285a2872.json", "country": "United States", "place_type": "city", "bounding_box": {"type": "Polygon", "coordinates": [[[-116.567788, 33.779426], [-116.567788, 33.870733], [-116.466791, 33.870733], [-116.466791, 33.779426]]]}, "country_code": "US", "attributes": {}, "id": "4265ece9285a2872", "name": "Palm Springs"}}{"contributors": null, "truncated": false, "text": "last year he was just my valentine but this year he's the loml \ud83d\udc96\ud83d\udc9c\ud83d\ude0d\u2026 https://t.co/Cp3aT4Jy86", "is_quote_status": false, "in_reply_to_status_id": null, "id": 699123010981068804, "favorite_count": 0, "rez": "Isabella Reservation", "source": "<a href=\"http://instagram.com\" rel=\"nofollow\">Instagram</a>", "retweeted": false, "coordinates": {"type": "Point", "coordinates": [-84.77398486, 43.58125036]}, "timestamp_ms": "1455518889552", "entities": {"user_mentions": [], "symbols": [], "hashtags": [], "urls": [{"url": "https://t.co/Cp3aT4Jy86", "indices": [68, 91], "expanded_url": "https://www.instagram.com/p/BBzBVFaQdHLSpCysWmPava5ElTjZhcDx97_zwc0/", "display_url": "instagram.com/p/BBzBVFaQdHLS\u2026"}]}, "in_reply_to_screen_name": null, "id_str": "699123010981068804", "retweet_count": 0, "in_reply_to_user_id": null, "favorited": false, "user": {"follow_request_sent": null, "profile_use_background_image": true, "default_profile_image": false, "id": 256076043, "verified": false, "profile_image_url_https": "https://pbs.twimg.com/profile_images/698415588859899904/GHrAa0sM_normal.jpg", "profile_sidebar_fill_color": "AA1FD9", "profile_text_color": "FFFAFF", "followers_count": 704, "profile_sidebar_border_color": "000000", "id_str": "256076043", "profile_background_color": "000000", "listed_count": 1, "profile_background_image_url_https": "https://pbs.twimg.com/profile_background_images/745181444/f52fb91478e1ef3847abb6d14bcc00b3.jpeg", "utc_offset": -21600, "statuses_count": 23541, "description": "\u264d\u2764\ufe0f\u264b\ufe0f\ufe0f", "friends_count": 432, "location": "mt pleasant ", "profile_link_color": "6420BD", "profile_image_url": "http://pbs.twimg.com/profile_images/698415588859899904/GHrAa0sM_normal.jpg", "following": null, "geo_enabled": true, "profile_banner_url": "https://pbs.twimg.com/profile_banners/256076043/1454876138", "profile_background_image_url": "http://pbs.twimg.com/profile_background_images/745181444/f52fb91478e1ef3847abb6d14bcc00b3.jpeg", "name": "samantha", "lang": "en", "profile_background_tile": true, "favourites_count": 38233, "screen_name": "samrosecan", "notifications": null, "url": "http://samrosecan.tumblr.com", "created_at": "Tue Feb 22 16:18:06 +0000 2011", "contributors_enabled": false, "time_zone": "Central Time (US & Canada)", "protected": false, "default_profile": false, "is_translator": false}, "geo": {"type": "Point", "coordinates": [43.58125036, -84.77398486]}, "in_reply_to_user_id_str": null, "possibly_sensitive": false, "lang": "en", "created_at": "Mon Feb 15 06:48:09 +0000 2016", "filter_level": "low", "in_reply_to_status_id_str": null, "place": {"full_name": "Mount Pleasant, MI", "url": "https://api.twitter.com/1.1/geo/id/77f923f5a841bbdf.json", "country": "United States", "place_type": "city", "bounding_box": {"type": "Polygon", "coordinates": [[[-84.816945, 43.553246], [-84.816945, 43.63446], [-84.727407, 43.63446], [-84.727407, 43.553246]]]}, "country_code": "US", "attributes": {}, "id": "77f923f5a841bbdf", "name": "Mount Pleasant"}}{"contributors": null, "truncated": false, "text": "My mom &amp; my son #twofavoritepeople @ Red Robin Gourmet Burgers https://t.co/2T5PFo1tK4", "is_quote_status": false, "in_reply_to_status_id": null, "id": 699119834311880704, "favorite_count": 0, "rez": "Gila River Indian Reservation", "source": "<a href=\"http://instagram.com\" rel=\"nofollow\">Instagram</a>", "retweeted": false, "coordinates": {"type": "Point", "coordinates": [-111.90010987, 33.30622032]}, "timestamp_ms": "1455518132175", "entities": {"user_mentions": [], "symbols": [], "hashtags": [{"indices": [20, 38], "text": "twofavoritepeople"}], "urls": [{"url": "https://t.co/2T5PFo1tK4", "indices": [67, 90], "expanded_url": "https://www.instagram.com/p/BBzAwXyP9wEeXJr9FoyKTGO8RyMvKVL6QJkz2s0/", "display_url": "instagram.com/p/BBzAwXyP9wEe\u2026"}]}, "in_reply_to_screen_name": null, "id_str": "699119834311880704", "retweet_count": 0, "in_reply_to_user_id": null, "favorited": false, "user": {"follow_request_sent": null, "profile_use_background_image": false, "default_profile_image": false, "id": 29408071, "verified": false, "profile_image_url_https": "https://pbs.twimg.com/profile_images/671180833760350208/BwFz62PG_normal.jpg", "profile_sidebar_fill_color": "7DDBA1", "profile_text_color": "CC9E70", "followers_count": 43, "profile_sidebar_border_color": "FFFFFF", "id_str": "29408071", "profile_background_color": "380C0C", "listed_count": 0, "profile_background_image_url_https": "https://pbs.twimg.com/profile_background_images/736713541/4afc430c2472fdc17c8da6ed63689d4e.png", "utc_offset": -25200, "statuses_count": 1056, "description": "Accept failure as part of the process", "friends_count": 96, "location": null, "profile_link_color": "C40E63", "profile_image_url": "http://pbs.twimg.com/profile_images/671180833760350208/BwFz62PG_normal.jpg", "following": null, "geo_enabled": true, "profile_banner_url": "https://pbs.twimg.com/profile_banners/29408071/1448856955", "profile_background_image_url": "http://pbs.twimg.com/profile_background_images/736713541/4afc430c2472fdc17c8da6ed63689d4e.png", "name": "Amy", "lang": "en", "profile_background_tile": true, "favourites_count": 28, "screen_name": "AmyRhodes_", "notifications": null, "url": null, "created_at": "Tue Apr 07 07:56:25 +0000 2009", "contributors_enabled": false, "time_zone": "Arizona", "protected": false, "default_profile": false, "is_translator": false}, "geo": {"type": "Point", "coordinates": [33.30622032, -111.90010987]}, "in_reply_to_user_id_str": null, "possibly_sensitive": false, "lang": "en", "created_at": "Mon Feb 15 06:35:32 +0000 2016", "filter_level": "low", "in_reply_to_status_id_str": null, "place": {"full_name": "Chandler, AZ", "url": "https://api.twitter.com/1.1/geo/id/52445186970bafb3.json", "country": "United States", "place_type": "city", "bounding_box": {"type": "Polygon", "coordinates": [[[-111.972849, 33.203761], [-111.972849, 33.36114], [-111.788898, 33.36114], [-111.788898, 33.203761]]]}, "country_code": "US", "attributes": {}, "id": "52445186970bafb3", "name": "Chandler"}}{"contributors": null, "truncated": false, "text": "You can never beat Arizona sunsets \u2764\ufe0f @ Gila River Indian Community https://t.co/nZ3nzgxIj2", "is_quote_status": false, "in_reply_to_status_id": null, "id": 699117210086805504, "favorite_count": 0, "rez": "Gila River Indian Reservation", "source": "<a href=\"http://instagram.com\" rel=\"nofollow\">Instagram</a>", "retweeted": false, "coordinates": {"type": "Point", "coordinates": [-111.76106877, 33.07531148]}, "timestamp_ms": "1455517506511", "entities": {"user_mentions": [], "symbols": [], "hashtags": [], "urls": [{"url": "https://t.co/nZ3nzgxIj2", "indices": [68, 91], "expanded_url": "https://www.instagram.com/p/BBy_j-hP994CHBkS4FCuAw5t8Zmmteh9FCNSOY0/", "display_url": "instagram.com/p/BBy_j-hP994C\u2026"}]}, "in_reply_to_screen_name": null, "id_str": "699117210086805504", "retweet_count": 0, "in_reply_to_user_id": null, "favorited": false, "user": {"follow_request_sent": null, "profile_use_background_image": false, "default_profile_image": false, "id": 29408071, "verified": false, "profile_image_url_https": "https://pbs.twimg.com/profile_images/671180833760350208/BwFz62PG_normal.jpg", "profile_sidebar_fill_color": "7DDBA1", "profile_text_color": "CC9E70", "followers_count": 43, "profile_sidebar_border_color": "FFFFFF", "id_str": "29408071", "profile_background_color": "380C0C", "listed_count": 0, "profile_background_image_url_https": "https://pbs.twimg.com/profile_background_images/736713541/4afc430c2472fdc17c8da6ed63689d4e.png", "utc_offset": -25200, "statuses_count": 1055, "description": "Accept failure as part of the process", "friends_count": 96, "location": null, "profile_link_color": "C40E63", "profile_image_url": "http://pbs.twimg.com/profile_images/671180833760350208/BwFz62PG_normal.jpg", "following": null, "geo_enabled": true, "profile_banner_url": "https://pbs.twimg.com/profile_banners/29408071/1448856955", "profile_background_image_url": "http://pbs.twimg.com/profile_background_images/736713541/4afc430c2472fdc17c8da6ed63689d4e.png", "name": "Amy", "lang": "en", "profile_background_tile": true, "favourites_count": 28, "screen_name": "AmyRhodes_", "notifications": null, "url": null, "created_at": "Tue Apr 07 07:56:25 +0000 2009", "contributors_enabled": false, "time_zone": "Arizona", "protected": false, "default_profile": false, "is_translator": false}, "geo": {"type": "Point", "coordinates": [33.07531148, -111.76106877]}, "in_reply_to_user_id_str": null, "possibly_sensitive": false, "lang": "en", "created_at": "Mon Feb 15 06:25:06 +0000 2016", "filter_level": "low", "in_reply_to_status_id_str": null, "place": {"full_name": "Arizona, USA", "url": "https://api.twitter.com/1.1/geo/id/a612c69b44b2e5da.json", "country": "United States", "place_type": "admin", "bounding_box": {"type": "Polygon", "coordinates": [[[-114.818269, 31.332246], [-114.818269, 37.004261], [-109.045153, 37.004261], [-109.045153, 31.332246]]]}, "country_code": "US", "attributes": {}, "id": "a612c69b44b2e5da", "name": "Arizona"}}