{"contributors": null, "truncated": false, "text": "rest up for that 12hr shift later. \ud83d\ude03\ud83d\udd2b (@ The House Of O\u2705 in Scottsdale, AZ) https://t.co/UEOi8itr3s", "is_quote_status": false, "in_reply_to_status_id": null, "id": 701014045659439104, "favorite_count": 0, "rez": "Salt River Reservation", "source": "<a href=\"http://foursquare.com\" rel=\"nofollow\">Foursquare</a>", "retweeted": false, "coordinates": {"type": "Point", "coordinates": [-111.86282053, 33.49899287]}, "timestamp_ms": "1455969747353", "entities": {"user_mentions": [], "symbols": [], "hashtags": [], "urls": [{"url": "https://t.co/UEOi8itr3s", "indices": [76, 99], "expanded_url": "https://www.swarmapp.com/c/9KdEiEnsTK6", "display_url": "swarmapp.com/c/9KdEiEnsTK6"}]}, "in_reply_to_screen_name": null, "id_str": "701014045659439104", "retweet_count": 0, "in_reply_to_user_id": null, "favorited": false, "user": {"follow_request_sent": null, "profile_use_background_image": true, "default_profile_image": false, "id": 2171773470, "verified": false, "profile_image_url_https": "https://pbs.twimg.com/profile_images/613466045324484609/AMXs5epW_normal.jpg", "profile_sidebar_fill_color": "DDEEF6", "profile_text_color": "333333", "followers_count": 89, "profile_sidebar_border_color": "C0DEED", "id_str": "2171773470", "profile_background_color": "C0DEED", "listed_count": 7, "profile_background_image_url_https": "https://abs.twimg.com/images/themes/theme1/bg.png", "utc_offset": null, "statuses_count": 9350, "description": "a born again hooligan only to be king again", "friends_count": 222, "location": "Scottsdale, AZ", "profile_link_color": "0084B4", "profile_image_url": "http://pbs.twimg.com/profile_images/613466045324484609/AMXs5epW_normal.jpg", "following": null, "geo_enabled": true, "profile_banner_url": "https://pbs.twimg.com/profile_banners/2171773470/1435096706", "profile_background_image_url": "http://abs.twimg.com/images/themes/theme1/bg.png", "name": "iGlaze", "lang": "en", "profile_background_tile": false, "favourites_count": 12235, "screen_name": "isaac_osif", "notifications": null, "url": "http://death-to-swag.tumblr.com", "created_at": "Sun Nov 03 08:13:15 +0000 2013", "contributors_enabled": false, "time_zone": null, "protected": false, "default_profile": true, "is_translator": false}, "geo": {"type": "Point", "coordinates": [33.49899287, -111.86282053]}, "in_reply_to_user_id_str": null, "possibly_sensitive": false, "lang": "en", "created_at": "Sat Feb 20 12:02:27 +0000 2016", "filter_level": "low", "in_reply_to_status_id_str": null, "place": {"full_name": "Arizona, USA", "url": "https://api.twitter.com/1.1/geo/id/a612c69b44b2e5da.json", "country": "United States", "place_type": "admin", "bounding_box": {"type": "Polygon", "coordinates": [[[-114.818269, 31.332246], [-114.818269, 37.004261], [-109.045153, 37.004261], [-109.045153, 31.332246]]]}, "country_code": "US", "attributes": {}, "id": "a612c69b44b2e5da", "name": "Arizona"}}
{"contributors": null, "truncated": false, "text": "Can you recommend anyone for this #job? Medical Assistant (MA) - https://t.co/SKwuVOkn96 #LumberBridge, NC #Hiring https://t.co/OG1jmw3iDw", "is_quote_status": false, "in_reply_to_status_id": null, "id": 701021440510853120, "favorite_count": 0, "rez": "Lumbee SDTSA", "source": "<a href=\"http://www.tweetmyjobs.com\" rel=\"nofollow\">TweetMyJOBS</a>", "retweeted": false, "coordinates": {"type": "Point", "coordinates": [-79.0722541, 34.8884971]}, "timestamp_ms": "1455971510423", "entities": {"user_mentions": [], "symbols": [], "hashtags": [{"indices": [34, 38], "text": "job"}, {"indices": [89, 102], "text": "LumberBridge"}, {"indices": [107, 114], "text": "Hiring"}], "urls": [{"url": "https://t.co/SKwuVOkn96", "indices": [65, 88], "expanded_url": "http://bit.ly/1SY2nB9", "display_url": "bit.ly/1SY2nB9"}], "media": [{"expanded_url": "http://twitter.com/PremiseJobs/status/701021440510853120/photo/1", "display_url": "pic.twitter.com/OG1jmw3iDw", "url": "https://t.co/OG1jmw3iDw", "media_url_https": "https://pbs.twimg.com/media/CbqHSS6UUAASAHj.jpg", "id_str": "701021440393367552", "sizes": {"small": {"h": 340, "resize": "fit", "w": 680}, "large": {"h": 512, "resize": "fit", "w": 1024}, "medium": {"h": 512, "resize": "fit", "w": 1024}, "thumb": {"h": 150, "resize": "crop", "w": 150}}, "indices": [115, 138], "type": "photo", "id": 701021440393367552, "media_url": "http://pbs.twimg.com/media/CbqHSS6UUAASAHj.jpg"}]}, "in_reply_to_screen_name": null, "id_str": "701021440510853120", "retweet_count": 0, "in_reply_to_user_id": null, "favorited": false, "user": {"follow_request_sent": null, "profile_use_background_image": false, "default_profile_image": false, "id": 3417954461, "verified": false, "profile_image_url_https": "https://pbs.twimg.com/profile_images/631467398290210816/9eqZ18px_normal.jpg", "profile_sidebar_fill_color": "000000", "profile_text_color": "000000", "followers_count": 352, "profile_sidebar_border_color": "000000", "id_str": "3417954461", "profile_background_color": "FFFFFF", "listed_count": 135, "profile_background_image_url_https": "https://abs.twimg.com/images/themes/theme1/bg.png", "utc_offset": null, "statuses_count": 768, "description": "Premise Health onsite health programs help people \u2013 and the organizations they work for \u2013 keep their edge, day after day.", "friends_count": 313, "location": null, "profile_link_color": "09578B", "profile_image_url": "http://pbs.twimg.com/profile_images/631467398290210816/9eqZ18px_normal.jpg", "following": null, "geo_enabled": true, "profile_banner_url": "https://pbs.twimg.com/profile_banners/3417954461/1439396533", "profile_background_image_url": "http://abs.twimg.com/images/themes/theme1/bg.png", "name": "Premise Health", "lang": "en", "profile_background_tile": false, "favourites_count": 0, "screen_name": "PremiseJobs", "notifications": null, "url": "http://www.premisehealth.com", "created_at": "Wed Aug 12 14:03:29 +0000 2015", "contributors_enabled": false, "time_zone": null, "protected": false, "default_profile": false, "is_translator": false}, "geo": {"type": "Point", "coordinates": [34.8884971, -79.0722541]}, "in_reply_to_user_id_str": null, "possibly_sensitive": false, "lang": "en", "created_at": "Sat Feb 20 12:31:50 +0000 2016", "filter_level": "low", "in_reply_to_status_id_str": null, "place": {"full_name": "North Carolina, USA", "url": "https://api.twitter.com/1.1/geo/id/3b98b02fba3f9753.json", "country": "United States", "place_type": "admin", "bounding_box": {"type": "Polygon", "coordinates": [[[-84.321948, 33.752879], [-84.321948, 36.588118], [-75.40012, 36.588118], [-75.40012, 33.752879]]]}, "country_code": "US", "attributes": {}, "id": "3b98b02fba3f9753", "name": "North Carolina"}, "extended_entities": {"media": [{"expanded_url": "http://twitter.com/PremiseJobs/status/701021440510853120/photo/1", "display_url": "pic.twitter.com/OG1jmw3iDw", "url": "https://t.co/OG1jmw3iDw", "media_url_https": "https://pbs.twimg.com/media/CbqHSS6UUAASAHj.jpg", "id_str": "701021440393367552", "sizes": {"small": {"h": 340, "resize": "fit", "w": 680}, "large": {"h": 512, "resize": "fit", "w": 1024}, "medium": {"h": 512, "resize": "fit", "w": 1024}, "thumb": {"h": 150, "resize": "crop", "w": 150}}, "indices": [115, 138], "type": "photo", "id": 701021440393367552, "media_url": "http://pbs.twimg.com/media/CbqHSS6UUAASAHj.jpg"}]}}
